curdleproofs/__init__.py
curdleproofs/commitment.py
curdleproofs/crs.py
curdleproofs/curdleproofs.py
curdleproofs/curdleproofs_transcript.py
curdleproofs/grand_prod.py
curdleproofs/ipa.py
curdleproofs/msm_accumulator.py
curdleproofs/opening.py
curdleproofs/py.typed
curdleproofs/same_msm.py
curdleproofs/same_perm.py
curdleproofs/same_scalar.py
curdleproofs/test_curdleproofs.py
curdleproofs/util.py
curdleproofs/whisk_interface.py
curdleproofs-0.1.2.dist-info/METADATA
curdleproofs-0.1.2.dist-info/WHEEL
curdleproofs-0.1.2.dist-info/RECORD
