Metadata-Version: 2.1
Name: curdleproofs
Version: 0.1.2
Summary: Curdleproofs is a zero-knowledge shuffle argument
License: MIT
Author: Nalin Bhardwaj
Author-email: nalinbhardwaj@nibnalin.me
Requires-Python: >=3.9,<4.0
Classifier: License :: OSI Approved :: MIT License
Classifier: Programming Language :: Python :: 3
Classifier: Programming Language :: Python :: 3.9
Classifier: Programming Language :: Python :: 3.10
Classifier: Programming Language :: Python :: 3.11
Classifier: Programming Language :: Python :: 3.12
Requires-Dist: merlin_transcripts (==0.1.1)
Requires-Dist: py_arkworks_bls12381 (>=0.3.5,<0.4.0)
